yk_utils/__init__.py
yk_utils/apis/__init__.py
yk_utils/apis/api_result.py
yk_utils/apis/base_url.py
yk_utils/apis/face_authentication.py
yk_utils/apis/http_requests.py
yk_utils/apis/key.py
yk_utils/apis/yoonik_api_exception.py
yk_utils/files/__init__.py
yk_utils/files/file_operations.py
yk_utils/images/__init__.py
yk_utils/images/image_parser.py
yk_utils/images/image_validation.py
yk_utils/models/__init__.py
yk_utils/models/base_enum.py
yk_utils/models/base_model.py
yk_utils/models/deserialization.py
yk_utils/models/error.py
yk_utils/models/str_base_enum.py
yk_utils/objects/__init__.py
yk_utils/objects/object_operations.py
yk_utils/web/__init__.py
yk_utils/web/exceptions.py
yk_utils/web/url_operations.py
yk_utils-1.3.6.dist-info/LICENSE
yk_utils-1.3.6.dist-info/METADATA
yk_utils-1.3.6.dist-info/WHEEL
yk_utils-1.3.6.dist-info/top_level.txt
yk_utils-1.3.6.dist-info/RECORD
