Metadata-Version: 2.1
Name: yk-utils
Version: 1.3.6
Summary: Youverse utils package for python.
Home-page: https://github.com/dev-yoonik/yk-utils-python
Author: Youverse
Author-email: tech@youverse.id
License: MIT
Classifier: Programming Language :: Python :: 3
Classifier: License :: OSI Approved :: MIT License
Classifier: Operating System :: OS Independent
Requires-Python: >=3.6
License-File: LICENSE
Requires-Dist: requests
Requires-Dist: beautifulsoup4
Requires-Dist: six
Requires-Dist: python-dateutil
Requires-Dist: httpx <1
